shortify/__init__.py
shortify/__main__.py
shortify/abc.py
shortify/constants.py
shortify/exceptions.py
shortify/main/app.py
shortify/main/cli.py
shortify/services/__init__.py
shortify/services/clck.py
shortify/services/git.py
shortify/services/isgd.py
shortify/services/shrtcode.py
shortify/services/tinyurl.py
shortify-0.6.0.dist-info/entry_points.txt
shortify-0.6.0.dist-info/LICENSE
shortify-0.6.0.dist-info/WHEEL
shortify-0.6.0.dist-info/METADATA
shortify-0.6.0.dist-info/RECORD
