Metadata-Version: 2.1
Name: shortify
Version: 0.6.0
Summary: A simple URL-shortening library with CLI support.
Home-page: https://github.com/Dositan/shortify
License: MIT
Keywords: url,shortener,cli
Author: Dastan Ozgeldi
Author-email: ozgdastan@gmail.com
Requires-Python: >=3.8,<4.0
Classifier: Development Status :: 5 - Production/Stable
Classifier: Intended Audience :: Developers
Classifier: Intended Audience :: End Users/Desktop
Classifier: License :: OSI Approved :: MIT License
Classifier: Natural Language :: English
Classifier: Operating System :: MacOS :: MacOS X
Classifier: Operating System :: Microsoft :: Windows
Classifier: Operating System :: POSIX :: Linux
Classifier: Programming Language :: Python :: 3
Classifier: Programming Language :: Python :: 3.8
Classifier: Programming Language :: Python :: 3.9
Requires-Dist: requests (==2.26.0)
Project-URL: Documentation, https://shortify.readthedocs.io/en/latest/
Project-URL: Repository, https://github.com/Dositan/shortify
